sma/__init__.py
sma/config.py
sma/enviroment.py
sma/log.py
sma/model.py
sma/prepared_queries.py
sma/prometheus.py
sma/report.py
sma/service.py
sma/sma.py
sma/utils.py
sustainability_measurement_agent-0.1.9.dist-info/licenses/LICENCE
sustainability_measurement_agent-0.1.9.dist-info/METADATA
sustainability_measurement_agent-0.1.9.dist-info/WHEEL
sustainability_measurement_agent-0.1.9.dist-info/top_level.txt
sustainability_measurement_agent-0.1.9.dist-info/RECORD
