Metadata-Version: 2.4
Name: sustainability-measurement-agent
Version: 0.1.9
Summary: Sustainability Measurement Agent - A tool for collecting and analyzing sustainability metrics in cloud native enviroments.
Author-email: Sebastian Werner <werner@tu-berlin.de>
Project-URL: Homepage, https://github.com/ISE-TU-Berlin/sustainability-measurement-agent
Keywords: sustainability,measurements,agent
Classifier: Programming Language :: Python :: 3.8
Classifier: Operating System :: OS Independent
Classifier: Topic :: Software Development :: Libraries
Classifier: Topic :: System :: Monitoring
Requires-Python: >=3.8
License-File: LICENCE
Requires-Dist: kubernetes
Requires-Dist: pyyaml
Requires-Dist: pandas>=2.3.0
Requires-Dist: numpy<2
Requires-Dist: requests
Requires-Dist: tables==3.9.2
Provides-Extra: test
Requires-Dist: pytest>=7.0; extra == "test"
Requires-Dist: pytest-kubernetes>=0.3.0; extra == "test"
Dynamic: license-file
